odoo9_addon_stock_no_negative-9.0.1.0.1-py2.7-nspkg.pth
odoo9_addon_stock_no_negative-9.0.1.0.1.dist-info/DESCRIPTION.rst
odoo9_addon_stock_no_negative-9.0.1.0.1.dist-info/METADATA
odoo9_addon_stock_no_negative-9.0.1.0.1.dist-info/RECORD
odoo9_addon_stock_no_negative-9.0.1.0.1.dist-info/WHEEL
odoo9_addon_stock_no_negative-9.0.1.0.1.dist-info/metadata.json
odoo9_addon_stock_no_negative-9.0.1.0.1.dist-info/namespace_packages.txt
odoo9_addon_stock_no_negative-9.0.1.0.1.dist-info/top_level.txt
odoo_addons/stock_no_negative/README.rst
odoo_addons/stock_no_negative/__init__.py
odoo_addons/stock_no_negative/__openerp__.py
odoo_addons/stock_no_negative/i18n/de.po
odoo_addons/stock_no_negative/i18n/es.po
odoo_addons/stock_no_negative/i18n/fr.po
odoo_addons/stock_no_negative/models/__init__.py
odoo_addons/stock_no_negative/models/product.py
odoo_addons/stock_no_negative/models/stock_quant.py
odoo_addons/stock_no_negative/tests/__init__.py
odoo_addons/stock_no_negative/tests/test_stock_no_negative.py
odoo_addons/stock_no_negative/views/product.xml
